accelerate/__init__.py
accelerate/python/__init__.py
accelerate/python/_argparse.py
accelerate/python/_collections.py
accelerate/python/_config.py
accelerate/python/_console.py
accelerate/python/_cryptography.py
accelerate/python/_dataclasses.py
accelerate/python/_exceptions.py
accelerate/python/_inspect.py
accelerate/python/_logging.py
accelerate/python/_microsoft.py
accelerate/python/_pandas.py
accelerate/python/_subprocess.py
accelerate/python/_threading.py
accelerate/python/_tracker.py
accelerate/python/_unittest.py
accelerate/python/_utils.py
accelerate_python-1.0.5.dist-info/METADATA
accelerate_python-1.0.5.dist-info/WHEEL
accelerate_python-1.0.5.dist-info/entry_points.txt
accelerate_python-1.0.5.dist-info/RECORD
