Metadata-Version: 2.1
Name: accelerate-python
Version: 1.0.5
Summary: Python utility package similar to apache-commons for Java
Author-Email: Rohit Narayanan <rohit.nn@gmail.com>
Requires-Python: >=3.12
Requires-Dist: coloredlogs>=15.0.1
Requires-Dist: jmespath>=1.0.1
Requires-Dist: jproperties>=2.1.2
Requires-Dist: pyyaml>=6.0.2
Requires-Dist: verboselogs>=1.7
